jsonty/__init__.py
jsonty/exceptions.py
jsonty/models.py
tests/test_dumps/__init__.py
tests/test_dumps/test_inheritance.py
tests/test_dumps/test_iteration.py
tests/test_dumps/test_simple_types.py
tests/test_dumps/test_typing.py
tests/test_loads/__init__.py
tests/test_loads/test_inheritance.py
tests/test_loads/test_iteration.py
tests/test_loads/test_simple_types.py
tests/util/__init__.py
tests/util/models.py
jsonty-0.2.0.dist-info/LICENSE
jsonty-0.2.0.dist-info/METADATA
jsonty-0.2.0.dist-info/WHEEL
jsonty-0.2.0.dist-info/top_level.txt
jsonty-0.2.0.dist-info/RECORD
