Metadata-Version: 2.1
Name: jsonty
Version: 0.2.0
Summary: Automatic custom class JSON serialization and deserialization
Home-page: https://github.com/AlbertFX91/jsonty
Author: Alberto Rojas
Author-email: alberto.rojas.fndez@gmail.com
License: BSD-2-Clause
Project-URL: Code, https://github.com/AlbertFX91/jsonty
Platform: UNKNOWN
Classifier: Programming Language :: Python :: 3
Classifier: Programming Language :: Python :: 3.7
Classifier: Programming Language :: Python :: 3.8
Classifier: Operating System :: OS Independent
